LICENSE.txt
README.md
setup.cfg
setup.py
zdiscord/__init__.py
zdiscord/config.py
zdiscord/discord.py
zdynamodb/__init__.py
zdynamodb/config.py
zdynamodb/dynamo.py
zdynamodb/queries.py
zdynamodb/setting.py
zrequests/__init__.py
zrequests/config.py
zrequests/requests.py
zrequests/setting.py
zrequests/z_requests.py
zs3/__init__.py
zs3/config.py
zs3/error_handler.py
zs3/s3.py
zs3/test.py
zservices.egg-info/PKG-INFO
zservices.egg-info/SOURCES.txt
zservices.egg-info/dependency_links.txt
zservices.egg-info/requires.txt
zservices.egg-info/top_level.txt
zsftp/__init__.py
zsftp/config.py
zsftp/queries.py
zsftp/sftp.py